odoo8_addon_account_invoice_entry_date-8.0.0.2.0-nspkg.pth
odoo_addons/account_invoice_entry_date/README.md
odoo_addons/account_invoice_entry_date/__init__.py
odoo_addons/account_invoice_entry_date/__openerp__.py
odoo_addons/account_invoice_entry_date/i18n/account_invoice_entry_date.pot
odoo_addons/account_invoice_entry_date/i18n/it.po
odoo_addons/account_invoice_entry_date/i18n/sl.po
odoo_addons/account_invoice_entry_date/models/__init__.py
odoo_addons/account_invoice_entry_date/models/account.py
odoo_addons/account_invoice_entry_date/static/description/icon.png
odoo_addons/account_invoice_entry_date/views/account_view.xml
odoo8_addon_account_invoice_entry_date-8.0.0.2.0.dist-info/METADATA
odoo8_addon_account_invoice_entry_date-8.0.0.2.0.dist-info/WHEEL
odoo8_addon_account_invoice_entry_date-8.0.0.2.0.dist-info/namespace_packages.txt
odoo8_addon_account_invoice_entry_date-8.0.0.2.0.dist-info/top_level.txt
odoo8_addon_account_invoice_entry_date-8.0.0.2.0.dist-info/RECORD
