Metadata-Version: 2.1
Name: odoo8-addon-account-invoice-entry-date
Version: 8.0.0.2.0
Summary: Account Invoice entry Date
Home-page: http://www.odoo-italia.org
Author: Odoo Italian Community,Odoo Community Association (OCA)
Author-email: support@odoo-community.org
License: AGPL-3
Platform: UNKNOWN
Classifier: Programming Language :: Python
Classifier: Framework :: Odoo
Classifier: License :: OSI Approved :: GNU Affero General Public License v3
Requires-Python: ~=2.7
Requires-Dist: odoo (<9.0a,>=8.0a)
